.gitignore
LICENSE.md
MANIFEST.in
README.md
requirements.txt
setup.cfg
setup.py
docs/Makefile
docs/make.bat
docs/source/conf.py
docs/source/index.rst
jp/__init__.py
jp.egg-info/PKG-INFO
jp.egg-info/SOURCES.txt
jp.egg-info/dependency_links.txt
jp.egg-info/entry_points.txt
jp.egg-info/not-zip-safe
jp.egg-info/requires.txt
jp.egg-info/top_level.txt
tests/__init__.py
tests/simple.jsonlines