Metadata-Version: 1.1
Name: jp
Version: 0.2.4
Summary: json print query filter
Home-page: https://github.com/hoffmann/jp
Author: Peter Hoffmann
Author-email: ph@peter-hoffmann.com
License: BSD
Platform: UNKNOWN
Classifier: Programming Language :: Python
